MANIFEST.in
requirements.txt
setup.py
lisa/__init__.py
lisa/plugins/__init__.py
lisa/plugins/Meteo/README.rst
lisa/plugins/Meteo/__init__.py
lisa/plugins/Meteo/meteo.json
lisa/plugins/Meteo/lang/en/LC_MESSAGES/meteo.mo
lisa/plugins/Meteo/lang/en/LC_MESSAGES/meteo.po
lisa/plugins/Meteo/lang/fr/LC_MESSAGES/meteo.mo
lisa/plugins/Meteo/lang/fr/LC_MESSAGES/meteo.po
lisa/plugins/Meteo/modules/__init__.py
lisa/plugins/Meteo/modules/meteo.py
lisa/plugins/Meteo/tests/meteo_test.py
lisa/plugins/Meteo/web/__init__.py
lisa/plugins/Meteo/web/api.py
lisa/plugins/Meteo/web/models.py
lisa/plugins/Meteo/web/tests.py
lisa/plugins/Meteo/web/urls.py
lisa/plugins/Meteo/web/views.py
lisa_plugin_Meteo.egg-info/PKG-INFO
lisa_plugin_Meteo.egg-info/SOURCES.txt
lisa_plugin_Meteo.egg-info/dependency_links.txt
lisa_plugin_Meteo.egg-info/namespace_packages.txt
lisa_plugin_Meteo.egg-info/requires.txt
lisa_plugin_Meteo.egg-info/top_level.txt